<annotation>
	<folder>img</folder>
	<filename>378979_11.jpg</filename>
	<path>/Users/manu/AndroidStudioProjects/pixial-training/img/378979_11.jpg</path>
	<source>
		<database>Unknown</database>
	</source>
	<size>
		<width>300</width>
		<height>442</height>
		<depth>3</depth>
	</size>
	<segmented>0</segmented>
	<object>
		<name>tit</name>
		<pose>Unspecified</pose>
		<truncated>0</truncated>
		<difficult>0</difficult>
		<bndbox>
			<xmin>11</xmin>
			<ymin>142</ymin>
			<xmax>48</xmax>
			<ymax>177</ymax>
		</bndbox>
	</object>
	<object>
		<name>tit</name>
		<pose>Unspecified</pose>
		<truncated>0</truncated>
		<difficult>0</difficult>
		<bndbox>
			<xmin>203</xmin>
			<ymin>56</ymin>
			<xmax>235</xmax>
			<ymax>90</ymax>
		</bndbox>
	</object>
</annotation>
