<annotation>
	<folder>train</folder>
	<filename>491384_05.jpg</filename>
	<path>/Users/manu/AndroidStudioProjects/object_detection_demo/data/images/train/491384_05.jpg</path>
	<source>
		<database>Unknown</database>
	</source>
	<size>
		<width>300</width>
		<height>431</height>
		<depth>3</depth>
	</size>
	<segmented>0</segmented>
	<object>
		<name>tit</name>
		<pose>Unspecified</pose>
		<truncated>0</truncated>
		<difficult>0</difficult>
		<bndbox>
			<xmin>59</xmin>
			<ymin>171</ymin>
			<xmax>100</xmax>
			<ymax>206</ymax>
		</bndbox>
	</object>
	<object>
		<name>tit</name>
		<pose>Unspecified</pose>
		<truncated>0</truncated>
		<difficult>0</difficult>
		<bndbox>
			<xmin>142</xmin>
			<ymin>169</ymin>
			<xmax>179</xmax>
			<ymax>205</ymax>
		</bndbox>
	</object>
	<object>
		<name>pussy</name>
		<pose>Unspecified</pose>
		<truncated>0</truncated>
		<difficult>0</difficult>
		<bndbox>
			<xmin>155</xmin>
			<ymin>329</ymin>
			<xmax>208</xmax>
			<ymax>367</ymax>
		</bndbox>
	</object>
</annotation>
